{"meta": {"mst": "1082547", "name": "군포시 방사능으로부터 안전한 식재료 공급 지원 조례", "dept": "교육체육과", "phone": "031-390-0581", "knd": "조례", "promulg_date": "20140520", "enforce_date": "20140520"}, "articles": [{"no": "제1조", "title": "목적", "html": "제1조(목적) 이 조례는 「영유아보육법」· 및 「경기도교육청 학교급식 방사능오염식재료 사용제한에 관한 조례」, 「군포시 학교급식 지원에 관한 조례」에 따라 실시하는 주요 시책의 실효성을 강화하고 학교 및 어린이집 급식에 방사성 물질이 들어간 식재료가 공급되지 않도록 함으로써 영유아 및 학생들의 건강과 안전을 지키는 것을 목적으로 한다.", "cites": 3, "act": 0}, {"no": "제2조", "title": "정의", "html": "제2조(정의) 이 조례에서 사용하는 용어의 정의는 다음과 같다.\n1. “방사성 물질”이란 세슘, 요오드, 스트론튬, 플로토늄 등 「원자력안전법」제2조제5호에 해당하는 물질을 말한다.\n2. “학교”란 <mark class=\"cite-law\" tabindex=\"0\" data-oc=\"제2조\" data-law=\"초·중등교육법\" data-clause=\"제2조\">「초·중등교육법」 제2조</mark>의 학교 및 「유아교육법」 제2조제2호에 따라 설립·운영되는 유치원을 말한다.\n3. “영유아”란 <mark class=\"cite-law\" tabindex=\"0\" data-oc=\"제2조\" data-law=\"영유아보육법\" data-clause=\"제2조\">「영유아보육법」 제2조</mark>의 어린이집에서 보육하는 6세 미만의 취학 전 아동을 말한다.", "cites": 4, "act": 2}, {"no": "제3조", "title": "시장의 책무", "html": "제3조(시장의 책무) 시장은 학교 및 영유아 급식에 방사성 물질이 포함된 식재료가 공급되지 않도록 검사를 실시·지원하고, 방사성 물질이 검출될 경우에는 해당 식재료 사용을 금지하기 위한 시책을 실시하여야 한다.", "cites": 0, "act": 0}, {"no": "제4조", "title": "방사성물질 검사 체계", "html": "제4조(방사성물질 검사 체계) \n① 시장은 「군포시 학교급식 지원 조례」에 의해 지원되는 식재료에 대해 방사성물질 검사와 관리가 체계적으로 이뤄지도록 해야 한다. \n② 시장은 어린이집급식에 사용되는 식재료를 정기 및 수시로 검사하여야 하되, 어린이집별로 연 2회 이상 사전 검사가 실시될 수 있도록 검사체계를 갖춰야 한다. 다만, 여러 어린이집에 공동으로 공급되는 식재료의 경우에는 일괄하여 검사할 수 있다. \n③ 시장은 관내 학교 및 어린이집 운영위원회에서 방사성 물질에 대한 식재료 검사를 실시할 때 필요한 장비와 인력을 지원해야 한다.", "cites": 1, "act": 0}, {"no": "제5조", "title": "급식안전센터의 설치", "html": "제5조(급식안전센터의 설치) \n① 시장은 제3조 및 제4조의 시행을 위해 학교 및 어린이집 급식 식재료의 검사를 위한 급식안전센터를 설치하여야 한다.\n② 시장은 1항의 급식안전센터의 운영 및 심의를 위해 급식안전위원회를 구성하며 각 호에 따라 위원을 선임한다. 단, 1호의 위원이 전체 위원의 1/2이 넘어야 하며, 위원회의 운영은 위원회 내규에 따른다.\n1. 관내 학교 및 어린이집의 보호자\n2. 보건소장 및 교육지원부서의 장\n3. 위원회에서 추천하는 급식 안전 전문가\n4. 시민사회단체에서 추천하는 급식안전 전문가", "cites": 0, "act": 0}, {"no": "제6조", "title": "정보공개", "html": "제6조(정보공개) 시장은 제4조에 따른 방사성 물질 검사 결과를 유효자리 한자리까지 표시하여 지체 없이 공개해야 한다.", "cites": 0, "act": 0}, {"no": "제7조", "title": "방사성물질 검출 식재료에 대한 조치", "html": "제7조(방사성물질 검출 식재료에 대한 조치) 시장은 방사성물질 검사결과 방사성물질이 검출된 경우에는 즉시 급식안전위원회 및 관련 학교운영위원회, 어린이집운영위원회에 통보하고 해당 식재료가 급식에 사용되지 않도록 해야 한다.", "cites": 0, "act": 0}, {"no": "제8조", "title": "교육 및 연수", "html": "제8조(교육 및 연수) \n① 시장은 어린이집 급식 관련 종사자의 교육 및 연수에 방사성 물질이 인체에 미치는 영향 등의 내용을 포함시켜야 한다. \n② 시장은 학부모 및 지역 주민들이 조례에 따른 식재료 안전 활동을 할 경우 필요한 교육이나 연수를 지원하여야 한다.", "cites": 0, "act": 0}, {"no": "제9조", "title": "자료제출 및 협조의 의무", "html": "제9조(자료제출 및 협조의 의무) 「영유아보육법」에 의해 시장의 지원을 받는 어린이집 운영자는 동 조례에 따른 시책에 적극 협조하여야 하며, 필요한 자료의 제출 요구에 응해야 한다.", "cites": 1, "act": 0}, {"no": "제10조", "title": "시행규칙", "html": "제10조(시행규칙) 이 조례의 시행에 필요한 사항은 규칙으로 정한다.", "cites": 0, "act": 0}], "local_refs": {"경기도교육청학교급식방사능오염식재료사용제한에관한조례": null, "군포시학교급식지원에관한조례": {"mst": "1563187", "name": "군포시 학교급식 지원에 관한 조례", "dept": "교육체육과", "enforce_date": "20210426"}, "군포시학교급식지원조례": null}, "law_refs": {"영유아보육법": {"name": "영유아보육법", "law_id": "000191", "clauses": ["제2조"], "counts": {"review": 1}, "local_admrul": false}, "원자력안전법": {"name": "원자력안전법", "law_id": "011435", "clauses": ["제2조"], "counts": {"current": 1}, "local_admrul": false}, "초·중등교육법": {"name": "초·중등교육법", "law_id": "000900", "clauses": ["제2조"], "counts": {"review": 1}, "local_admrul": false}, "유아교육법": {"name": "유아교육법", "law_id": "009621", "clauses": ["제2조"], "counts": {"current": 1}, "local_admrul": false}}, "features": {"law": 4, "admrul": 0, "local": 3}, "recommend": {"found": true, "mst": "1082547", "name": "군포시 방사능으로부터 안전한 식재료 공급 지원 조례", "grades": {"mechanical": 0, "review": 2, "check": 0, "format": 0, "current": 2}, "items_count": 4, "html": "<div class=\"ord\"><h2>군포시 방사능으로부터 안전한 식재료 공급 지원 조례</h2><div class=\"meta\">시행 2014-05-20 · 정비 항목 4건 · 조례 조문 순서로 정렬</div><div class=\"badges\"><span class=\"badge b-rev\">⚠️ 검토 필요 2</span></div><div class=\"artsec\" data-oc=\"제2조\"><div class=\"arthd\">조례 제2조</div><details class=\"item citem cur\" data-sev=\"current\" data-oc=\"제2조\" data-law=\"원자력안전법\" data-clause=\"제2조\"><summary class=\"iline\"><span class=\"tag t-cur\">✅ 변경 없음</span><span class=\"law\"><span class=\"ki\" title=\"상위법령\">⚖</span> 「원자력안전법」 제2조제5호</span></summary><div class=\"act\">검토 완료 — 인용 조항이 조례 시행 이후 개정되지 않아 변경 없음.</div><div class=\"basis\">기준일 — 조례 시행 <b>2014-05-20</b> · 당시 법령본 <b>2013-03-23</b> → 현행 조문 <b>2024-10-22</b></div></details><details class=\"item citem\" data-sev=\"review\" data-oc=\"제2조\" data-law=\"초·중등교육법\" data-clause=\"제2조\"><summary class=\"iline\"><span class=\"tag t-rev\">내용변경</span><span class=\"law\"><span class=\"ki\" title=\"상위법령\">⚖</span> 「초·중등교육법」 제2조</span></summary><div class=\"act\">「초·중등교육법」 제2조 개정 내용을 반영하여 이 조례 제2조을(를) 검토·정비</div><div class=\"basis\">기준일 — 조례 시행 <b>2014-05-20</b> · 당시 법령본 <b>원제정</b> → 현행 조문 <b>2019-12-03</b></div><div class=\"diff\"><div class=\"diff-uni\">제2조(학교의 종류) 초ㆍ중등교육을 실시하기 위하여 다음 각 호의 학교를 둔다.<mark class=\"i\"> &lt;개정 2019.12.3&gt;</mark>\n1.  <mark class=\"d\">초등학교ㆍ공민학교</mark><mark class=\"i\">초등학교</mark>\n2.  중학교ㆍ고등공민학교\n3.  고등학교ㆍ고등기술학교\n4.  특수학교\n5.  각종학교</div><div class=\"diff-split\"><div class=\"drow\"><span class=\"dlabel was\">당시</span><span class=\"dtext\">제2조(학교의 종류) 초ㆍ중등교육을 실시하기 위하여 다음 각 호의 학교를 둔다.<mark class=\"pt\" title=\"&lt;개정 2019.12.3&gt; 추가됨\">‸</mark>\n1.  <mark class=\"d\">초등학교ㆍ공민학교</mark>\n2.  중학교ㆍ고등공민학교\n3.  고등학교ㆍ고등기술학교\n4.  특수학교\n5.  각종학교</span></div><div class=\"drow\"><span class=\"dlabel now\">현행</span><span class=\"dtext\">제2조(학교의 종류) 초ㆍ중등교육을 실시하기 위하여 다음 각 호의 학교를 둔다.<mark class=\"i\"> &lt;개정 2019.12.3&gt;</mark>\n1.  <mark class=\"i\">초등학교</mark>\n2.  중학교ㆍ고등공민학교\n3.  고등학교ㆍ고등기술학교\n4.  특수학교\n5.  각종학교</span></div></div></div></details><details class=\"item citem cur\" data-sev=\"current\" data-oc=\"제2조\" data-law=\"유아교육법\" data-clause=\"제2조\"><summary class=\"iline\"><span class=\"tag t-cur\">✅ 변경 없음</span><span class=\"law\"><span class=\"ki\" title=\"상위법령\">⚖</span> 「유아교육법」 제2조제2호</span></summary><div class=\"act\">검토 완료 — 인용 조항이 조례 시행 이후 개정되지 않아 변경 없음.</div><div class=\"basis\">기준일 — 조례 시행 <b>2014-05-20</b> · 당시 법령본 <b>2012-03-21</b> → 현행 조문 <b>2012-03-21</b></div></details><details class=\"item citem\" data-sev=\"review\" data-oc=\"제2조\" data-law=\"영유아보육법\" data-clause=\"제2조\"><summary class=\"iline\"><span class=\"tag t-rev\">내용변경</span><span class=\"law\"><span class=\"ki\" title=\"상위법령\">⚖</span> 「영유아보육법」 제2조</span></summary><div class=\"act\">「영유아보육법」 제2조 개정 내용을 반영하여 이 조례 제2조을(를) 검토·정비</div><div class=\"basis\">기준일 — 조례 시행 <b>2014-05-20</b> · 당시 법령본 <b>2011-06-07</b> → 현행 조문 <b>2024-02-06</b></div><div class=\"diff\"><div class=\"diff-uni\">제2조(정의) 이 법에서 사용하는 용어의 뜻은 다음과 같다. &lt;개정 2008.12.19, 2011.6.7<mark class=\"i\">, 2023.8.8, 2024.2.6</mark>&gt;\n1.  &quot;영유아&quot;란 <mark class=\"d\">6세</mark><mark class=\"i\">7세</mark> <mark class=\"d\">미만의</mark><mark class=\"i\">이하의</mark> 취학 전 아동을 말한다.\n2.  &quot;보육&quot;이란 영유아를 건강하고 안전하게 보호ㆍ양육하고 영유아의 발달 특성에 맞는 교육을 제공하는 어린이집 및 가정양육 지원에 관한 사회복지서비스를 말한다.\n3.  &quot;어린이집&quot;이란 <mark class=\"d\">보호자의</mark><mark class=\"i\">영유아의</mark> <mark class=\"d\">위탁을</mark><mark class=\"i\">보육을</mark> <mark class=\"d\">받아</mark><mark class=\"i\">위하여</mark> <mark class=\"d\">영유아를</mark><mark class=\"i\">이</mark> <mark class=\"d\">보육하는</mark><mark class=\"i\">법에 따라 설립ㆍ운영되는</mark> 기관을 말한다.\n4.  &quot;보호자&quot;란 친권자ㆍ후견인, 그 밖의 자로서 영유아를 사실상 보호하고 있는 자를 말한다.\n5.  &quot;보육교직원&quot;이란 어린이집 영유아의 보육, 건강관리 및 보호자와의 상담, 그 밖에 어린이집의 관리ㆍ운영 등의 업무를 담당하는 자로서 어린이집의 원장 및 보육교사와 그 밖의 직원을 말한다.</div><div class=\"diff-split\"><div class=\"drow\"><span class=\"dlabel was\">당시</span><span class=\"dtext\">제2조(정의) 이 법에서 사용하는 용어의 뜻은 다음과 같다. &lt;개정 2008.12.19, 2011.6.7<mark class=\"pt\" title=\", 2023.8.8, 2024.2.6 추가됨\">‸</mark>&gt;\n1.  &quot;영유아&quot;란 <mark class=\"d\">6세</mark> <mark class=\"d\">미만의</mark> 취학 전 아동을 말한다.\n2.  &quot;보육&quot;이란 영유아를 건강하고 안전하게 보호ㆍ양육하고 영유아의 발달 특성에 맞는 교육을 제공하는 어린이집 및 가정양육 지원에 관한 사회복지서비스를 말한다.\n3.  &quot;어린이집&quot;이란 <mark class=\"d\">보호자의</mark> <mark class=\"d\">위탁을</mark> <mark class=\"d\">받아</mark> <mark class=\"d\">영유아를</mark> <mark class=\"d\">보육하는</mark> 기관을 말한다.\n4.  &quot;보호자&quot;란 친권자ㆍ후견인, 그 밖의 자로서 영유아를 사실상 보호하고 있는 자를 말한다.\n5.  &quot;보육교직원&quot;이란 어린이집 영유아의 보육, 건강관리 및 보호자와의 상담, 그 밖에 어린이집의 관리ㆍ운영 등의 업무를 담당하는 자로서 어린이집의 원장 및 보육교사와 그 밖의 직원을 말한다.</span></div><div class=\"drow\"><span class=\"dlabel now\">현행</span><span class=\"dtext\">제2조(정의) 이 법에서 사용하는 용어의 뜻은 다음과 같다. &lt;개정 2008.12.19, 2011.6.7<mark class=\"i\">, 2023.8.8, 2024.2.6</mark>&gt;\n1.  &quot;영유아&quot;란 <mark class=\"i\">7세</mark> <mark class=\"i\">이하의</mark> 취학 전 아동을 말한다.\n2.  &quot;보육&quot;이란 영유아를 건강하고 안전하게 보호ㆍ양육하고 영유아의 발달 특성에 맞는 교육을 제공하는 어린이집 및 가정양육 지원에 관한 사회복지서비스를 말한다.\n3.  &quot;어린이집&quot;이란 <mark class=\"i\">영유아의</mark> <mark class=\"i\">보육을</mark> <mark class=\"i\">위하여</mark> <mark class=\"i\">이</mark> <mark class=\"i\">법에 따라 설립ㆍ운영되는</mark> 기관을 말한다.\n4.  &quot;보호자&quot;란 친권자ㆍ후견인, 그 밖의 자로서 영유아를 사실상 보호하고 있는 자를 말한다.\n5.  &quot;보육교직원&quot;이란 어린이집 영유아의 보육, 건강관리 및 보호자와의 상담, 그 밖에 어린이집의 관리ㆍ운영 등의 업무를 담당하는 자로서 어린이집의 원장 및 보육교사와 그 밖의 직원을 말한다.</span></div></div></div></details></div></div>", "css": "\n/* 변수는 .page(독립 권고서)·.ord(대시보드 주입 블록)에만 — :root 로 두면 대시보드의\n   자체 변수를 덮어써 색이 바뀐다. 두 루트에 한정해 주입 시 오염을 막는다. */\n.page, .ord { --navy:#13325b; --navy2:#1d4e89;\n  --mech:#1d4ed8; --rev:#b45309; --chk:#52525b; --fmt:#6d28d9; --cur:#15803d;\n  --ink:#1f2937; --muted:#6b7280; --line:#d8dee6; --soft:#f6f8fb; }\n* { box-sizing: border-box; }\n/* 독립 권고서 페이지 한정(body.report·.page) — 대시보드 주입 시 충돌 방지.\n   대시보드는 자체 body/h1/.cards/.sub/.card 를 가져 prefix 없으면 덮어쓴다. */\nbody.report { font-family: \"Malgun Gothic\",\"맑은 고딕\",system-ui,sans-serif;\n       color:var(--ink); margin:0; background:#eef1f5; line-height:1.55;\n       -webkit-text-size-adjust:100%; }\n.page { max-width:840px; margin:24px auto; padding:38px 44px 52px; background:#fff;\n        border-top:4px solid var(--navy); box-shadow:0 1px 5px rgba(15,33,66,.10); }\n/* 문서 머리 — 공문 단정형(머리표·제목·요지, 아래 굵은 밑줄) */\n.page .dochd { border-bottom:2px solid var(--navy); padding-bottom:13px; margin-bottom:22px; }\n.page .dochd .kicker { font-size:11.5px; letter-spacing:3px; color:var(--navy2);\n        font-weight:700; margin:0 0 6px; }\n.page h1 { font-size:22px; line-height:1.34; margin:0; color:var(--navy);\n     font-weight:700; letter-spacing:-.3px; }\n.page .sub { color:var(--muted); font-size:12.5px; margin-top:7px; }\n.page .cards { display:flex; gap:10px; flex-wrap:wrap; margin:0 0 20px; }\n.page .card { flex:1 1 138px; border:1px solid var(--line); border-top:3px solid var(--chk);\n        border-radius:6px; padding:12px 15px; }\n.page .card .n { font-size:25px; font-weight:700; line-height:1; color:var(--ink); }\n.page .card .t { font-size:12.5px; color:var(--muted); margin-top:6px; }\n.page .g-mech { border-top-color:var(--mech);} .page .g-mech .n { color:var(--mech);}\n.page .g-rev { border-top-color:var(--rev);} .page .g-rev .n { color:var(--rev);}\n.page .g-chk { border-top-color:var(--chk);} .page .g-chk .n { color:var(--chk);}\n.page .g-fmt { border-top-color:var(--fmt);} .page .g-fmt .n { color:var(--fmt);}\n.page .g-cur { border-top-color:var(--cur);} .page .g-cur .n { color:var(--cur);}\n.ord { border:1px solid var(--line); border-radius:7px; padding:18px 20px;\n       margin:0 0 16px; page-break-inside:avoid; }\n.ord h2 { font-size:16.5px; margin:0 0 3px; color:var(--navy); font-weight:700;\n          padding-left:10px; border-left:4px solid var(--navy); }\n.ord .meta { color:var(--muted); font-size:12px; margin:0 0 12px; padding-left:14px; }\n.badges { margin:0 0 12px; }\n.badge { display:inline-block; font-size:11.5px; padding:2px 10px; border-radius:4px;\n         margin-right:6px; border:1px solid currentColor; background:#fff; font-weight:600; }\n.b-mech { color:var(--mech);} .b-rev { color:var(--rev);}\n.b-chk { color:var(--chk);} .b-fmt { color:var(--fmt);}\n.artsec { margin:0 0 8px; }\n.arthd { font-size:13px; font-weight:700; color:var(--navy); background:var(--soft);\n         border-left:3px solid var(--navy2); padding:5px 11px; border-radius:0 4px 4px 0;\n         margin:14px 0 6px; }\n.item { border-top:1px solid #f3f4f6; padding:9px 0 9px 10px; }\n.iline { margin-bottom:3px; }\n.item .tag { font-size:11px; font-weight:700; padding:1px 7px; border-radius:6px;\n             margin-right:8px; white-space:nowrap; }\n.t-mech { background:#dbeafe; color:#1e40af;} .t-rev { background:#fef3c7; color:#92400e;}\n.t-chk { background:#f3f4f6; color:#374151;}\n.t-naked { background:#ede9fe; color:#5b21b6;}\n.t-cur { background:#dcfce7; color:#166534;}\n.t-space { background:#fef9c3; color:#854d0e;}\ndetails.citem.cur > summary { opacity:.72; }\ndetails.citem.cur .law { font-weight:500; }\n/* 접이식 인용 항목(대시보드 우측) — 기본 접힘, 좌측 인용 클릭 시 펼침 */\ndetails.citem { border-top:1px solid #f3f4f6; padding:0; border-left:4px solid transparent; }\n/* 심각도 좌측 색바(4px) — .focus 는 box-shadow 라 색바와 공존 */\ndetails.citem[data-sev=\"mechanical\"] { border-left-color:var(--mech); }\ndetails.citem[data-sev=\"review\"] { border-left-color:var(--rev); }\ndetails.citem[data-sev=\"check\"] { border-left-color:var(--chk); }\ndetails.citem[data-sev=\"format\"] { border-left-color:var(--fmt); }\ndetails.citem[data-sev=\"current\"] { border-left-color:#d1d5db; }\n/* 변경없음 숨기기(우측 헤더 체크) — .drec 는 serve.py 컨테이너 */\n.drec.hide-cur details.citem.cur { display:none; }\ndetails.citem > summary { list-style:none; cursor:pointer; padding:9px 10px 9px 8px;\n    display:flex; align-items:center; gap:5px; flex-wrap:wrap; }\ndetails.citem > summary::-webkit-details-marker { display:none; }\ndetails.citem > summary::before { content:\"▸\"; color:#9ca3af; font-size:11px; margin-right:2px; }\ndetails.citem[open] > summary::before { content:\"▾\"; color:var(--navy2); }\ndetails.citem[open] { background:#fbfcfe; }\ndetails.citem > .act { padding:2px 10px 0; } details.citem > .basis { padding:0 10px; }\ndetails.citem > .diff { margin:6px 10px 10px; }\ndetails.citem.focus { box-shadow:inset 3px 0 0 var(--navy2); }\n.item .law { font-size:13px; font-weight:600; color:#374151; }\n.item .law .ki { font-weight:400; font-size:12px; margin-right:1px; }\n.item .act { font-size:13.5px; margin:3px 0; color:var(--ink); }\n/* 검토 문안 내 정정 강조 — 현재 표기(회색) → 정정 표기(초록), 삽입 「」는 진한 초록 */\n.act .fx-old { background:#f1f5f9; color:#64748b; border-radius:3px; padding:0 3px; }\n.act .fx-new { background:#eafaf0; color:#15803d; border-radius:3px; padding:0 3px; font-weight:600; }\n.act .fx-new .fx-brk { background:#bbf7d0; color:#166534; font-weight:800; border-radius:2px;\n    padding:0 1px; margin:0 1px; text-decoration:none; }\n.basis { font-size:11.5px; color:var(--muted); margin:4px 0 6px; }\n.basis b { color:#374151; font-weight:600; }\n.ordtext { font-size:12.5px; color:var(--ink); background:var(--soft); border:1px solid var(--line);\n           border-left:3px solid var(--navy2); border-radius:0 6px 6px 0; padding:8px 11px;\n           margin:5px 0 9px; white-space:pre-wrap; line-height:1.7; }\n.ordtext b { color:var(--navy); margin-right:5px; }\nmark.cite-law { background:#eff6ff; color:#1e3a8a;\n   text-decoration:underline; text-decoration-color:#2563eb; text-underline-offset:2px;\n   border-radius:2px; padding:0 1px; }\nmark.cite-naked { background:#f5f3ff; color:#5b21b6;\n   text-decoration:underline dashed; text-decoration-color:#7c3aed; text-underline-offset:2px;\n   border-radius:2px; padding:0 1px; }\nmark.cite-local { background:#f1f5f9; color:#475569;\n   text-decoration:underline dotted; text-decoration-color:#94a3b8; text-underline-offset:2px;\n   border-radius:2px; padding:0 1px; }\n.page .leg { font-size:12px; color:var(--muted); margin:0 0 18px; display:flex; gap:14px;\n        flex-wrap:wrap; align-items:center; }\n.page .leg mark { padding:0 4px; border-radius:2px; }\n.item .ev { font-size:12px; color:#6b7280; white-space:pre-wrap;\n            background:#f9fafb; border-radius:6px; padding:7px 9px; margin-top:6px; }\n.diff { border:1px solid #eef0f3; border-radius:6px; overflow:hidden; margin-top:6px; }\n.diff .diff-uni { font-size:12px; padding:7px 9px; white-space:pre-wrap;\n  word-break:keep-all; overflow-wrap:anywhere; color:#374151; line-height:1.55; }\n.diff .diff-split { display:none; }                 /* 대시보드 기본 = 통합(합쳐) 보기 */\n/* 나란히 모드(대시보드 토글) · 인쇄 권고서(.page)는 당시·현행 나란히 */\n.diff-mode-split .diff .diff-uni, .page .diff .diff-uni { display:none; }\n.diff-mode-split .diff .diff-split, .page .diff .diff-split { display:block; }\n.drow { display:flex; gap:8px; font-size:12px; padding:6px 9px; }\n.drow + .drow { border-top:1px solid #f1f3f5; }\n.dlabel { flex:0 0 34px; font-weight:700; font-size:11px; padding-top:1px; }\n.dlabel.was { color:#b91c1c; } .dlabel.now { color:#15803d; }\n.dtext { flex:1; white-space:pre-wrap; word-break:keep-all; overflow-wrap:anywhere; color:#374151; line-height:1.5; }\nmark.d { background:#fee2e2; color:#991b1b; text-decoration:line-through;\n         border-radius:2px; padding:0 1px; }\nmark.i { background:#dcfce7; color:#166534; border-radius:2px; padding:0 1px; }\nmark.pt { background:#fee2e2; color:#dc2626; font-weight:700; border-radius:2px;\n          padding:0 2px; cursor:help; }\n.page footer { color:#9aa3af; font-size:11.5px; margin-top:34px; padding-top:14px;\n         border-top:1px solid var(--line); text-align:center; }\n@media print {\n  @page { size:A4; margin:16mm; }\n  body { background:#fff; }\n  .page { max-width:none; margin:0; padding:0; border-top:none; box-shadow:none; }\n  .ord, .card { border-color:#c4cbd4; }\n  .dochd { border-bottom-color:#000; }\n  mark.d, mark.i, mark.pt, .ordtext mark, .card, .badge {\n    -webkit-print-color-adjust:exact; print-color-adjust:exact; }\n}\n"}}