{"meta": {"mst": "2106123", "name": "군포시 청소년재단 설립 및 운영 조례", "dept": "아동청소년과", "phone": "031-390-0189", "knd": "조례", "promulg_date": "20260107", "enforce_date": "20260107"}, "articles": [{"no": "제1조", "title": "목적", "html": "제1조(목적) 이 조례는 군포시 청소년에 대한 효율적인 지원과 건전한 육성의 진흥을 위하여 군포시 청소년재단을 설립하고 그 운영에 필요한 사항을 규정함을 목적으로 한다.", "cites": 0, "act": 0}, {"no": "제2조", "title": "적용범위", "html": "제2조(적용범위) 군포시 청소년재단(이하 “재단”이라 한다)의 설립·운영에 관하여는 <mark class=\"cite-current\" tabindex=\"0\" data-oc=\"제2조\" data-law=\"민법\" data-clause=\"\">「민법」</mark> 및 <mark class=\"cite-current\" tabindex=\"0\" data-oc=\"제2조\" data-law=\"지방자치단체 출자·출연 기관의 운영에 관한 법률\" data-clause=\"\">「지방자치단체 출자·출연 기관의 운영에 관한 법률」</mark> 등 관계 법령에서 달리 정하는 경우를 제외하고는 이 조례가 정하는 바에 따른다.", "cites": 2, "act": 0}, {"no": "제3조", "title": "설립", "html": "제3조(설립) 재단은<mark class=\"cite-current\" tabindex=\"0\" data-oc=\"제3조\" data-law=\"민법\" data-clause=\"\">「민법」</mark>에 따른 재단법인으로 설립한다.", "cites": 1, "act": 0}, {"no": "제4조", "title": "재단의 사업", "html": "제4조(재단의 사업) 재단은 다음 각 호의 사업을 수행한다.\n1. 청소년 활동 진흥에 관한 사업\n2. 청소년 보호·복지·상담에 관한 사업\n3. 군포시(이하 “시”라 한다)가 위탁한 청소년 시설에 대한 운영·관리\n4. 학교 교육과정 연계·지원에 관한 사업\n5. 시민의 복지증진과 건전한 청소년육성을 위한 사업\n6. 그 밖에 군포시장(이하 “시장”이라 한다)이 승인하는 사업", "cites": 0, "act": 0}, {"no": "제5조", "title": "기본재산의 조성", "html": "제5조(기본재산의 조성) 재단의 기본재산은 다음 각 호의 재원으로 조성한다.\n1. 시의 출연금\n2. 재단사업 수입금\n3. 그밖의 수입금", "cites": 0, "act": 0}, {"no": "제6조", "title": "정관", "html": "제6조(정관) \n① 재단의 정관에는 다음 각 호의 사항을 기재하여야 한다.\n1. 목적\n2. 명칭\n3. 사무소의 소재지\n4. 자산 및 예산·회계에 관한 사항\n5. 이사의 임면에 관한 사항\n6. 이사회에 관한 사항\n7. 감사 및 직원에 관한 사항\n8. 공고에 관한 사항\n9. 사업에 관한 사항\n10. 정관 변경에 관한 사항\n11. 해산에 관한 사항\n12. 그밖에 재단의 운영에 필요한 사항\n② 재단이 정관을 제정 또는 변경하고자 할 때에는 사전에 시장의 승인을 받아야 한다.", "cites": 0, "act": 0}, {"no": "제7조", "title": "임원 등", "html": "제7조(임원 등) \n① 재단에는 이사장 및 대표이사를 포함한 15명 이내의 이사와 감사 2명을 둔다.\n② 이사장은 시장으로 한다.\n③ 대표이사·이사 및 감사의 임기와 임면에 관한 사항은 정관이 정하는 바에 따른다.\n④ 대표이사를 제외한 이사 및 감사는 비상근으로 한다.", "cites": 0, "act": 0}, {"no": "제8조", "title": "임원의 직무", "html": "제8조(임원의 직무) \n① 이사장은 이사회를 소집하며 그 의장이 된다.\n② 이사장은 재단을 대표하고 재단의 업무를 총괄하며, 이사장의 직무 및 대행에 관한 사항은 정관이 정하는 바에 따른다. &lt;개정 2022.4.25.&gt;\n③ 감사는 재단의 업무와 회계를 감사하며 이사회에 출석하여 의견을 진술할 수 있다.", "cites": 0, "act": 0}, {"no": "제9조", "title": "이사회의 구성 및 운영", "html": "제9조(이사회의 구성 및 운영) \n① 재단에 이사회를 두되, 이사회는 이사장, 대표이사 및 이사로 구성한다.\n② 이사회는 정관이 정하는 바에 따라 재단의 업무에 관한 중요한 사항을 심의·의결한다.\n③ 이사회는 이사장이 필요하다고 인정하는 경우 또는 재적이사 3분의 1 이상의 요구가 있을 경우에 소집하고, 이사장이 이사회에 관한 사항을 운영한다.\n④ 이사회는 재적이사 과반수의 출석으로 개의하고, 출석이사 과반수의 찬성으로 의결한다.", "cites": 0, "act": 0}, {"no": "제10조", "title": "직원", "html": "제10조(직원) 재단의 직원은 정관이 정하는 바에 따라 이사장이 임면한다.", "cites": 0, "act": 0}, {"no": "제11조", "title": "운영재원", "html": "제11조(운영재원) 재단의 운영 및 사업에 필요한 재원은 제5조에 따른 기본재산으로 충당한다.", "cites": 0, "act": 0}, {"no": "제12조", "title": "수익사업", "html": "제12조(수익사업) 재단은 <mark class=\"cite-naked\" tabindex=\"0\" data-oc=\"제12조\" data-law=\"청소년기본법\" data-clause=\"제30조\">청소년기본법 제30조</mark> 및 정관에서 정하는 바에 따라 청소년 육성과 관련한 수익사업을 할 수 있다.", "cites": 1, "act": 1}, {"no": "제13조", "title": "사업연도", "html": "제13조(사업연도) 재단의 사업연도는 시의 일반회계 회계연도에 따른다.", "cites": 0, "act": 0}, {"no": "제14조", "title": "사업계획서 등의 제출", "html": "제14조(사업계획서 등의 제출) 재단은 매 사업연도마다 사업계획서와 예산을 작성하여 회계연도 개시 40일 전까지 이사회의 의결을 거쳐 시장의 승인을 받은 후 군포시의회(이하 &quot;시의회&quot;라 한다.)에 제출하여야 한다. 예산 총액 규모가 변경될 경우에도 또한 같다. &lt;개정 2021.4.26., 2026.1.7.&gt;", "cites": 0, "act": 0}, {"no": "제15조", "title": "결산서의 제출", "html": "제15조(결산서의 제출) 재단은 매 사업연도마다 사업실적 및 세입·세출 결산서를 작성하여 이사회의 의결을 거친 후 다음 회계연도 3월 말까지 시장에게 제출한 후 시의회에 제출하여야 한다. &lt;개정 2026.1.7.&gt;", "cites": 0, "act": 0}, {"no": "제16조", "title": "공유재산 무상사용 등", "html": "제16조(공유재산 무상사용 등) \n① 시장은 필요한 경우에 재단의 재산을 무상으로 사용할 수 있다.\n② 시장은 재단의 설립과 운영을 위하여 필요한 경우에는 공유재산(물품을 포함한다)을 무상대부(무상사용 수익을 포함한다)할 수 있다. 다만, 공용·공공용 또는 공익사업에 직접 사용하지 아니하고 제12조에 따른 수익사업을 위하여 사용하는 재산에 대하여는 그러하지 아니하다.", "cites": 0, "act": 0}, {"no": "제17조", "title": "잔여재산의 귀속", "html": "제17조(잔여재산의 귀속) 재단의 해산 시 잔여재산은 정관에 따라 시에 귀속된다.", "cites": 0, "act": 0}, {"no": "제18조", "title": "보고·검사·감사", "html": "제18조(보고·검사·감사) \n① 시장은 재단의 경영상황 및 필요한 사항에 대하여 보고·검사·감사를 요청할 수 있으며 재단은 이에 응하여야 한다.\n② 시장은 소속공무원에게 그 업무를 확인·검사하게 할 수 있다.", "cites": 0, "act": 0}, {"no": "제19조", "title": "공무원의 파견", "html": "제19조(공무원의 파견) 시장은 재단의 설립 목적을 달성하기 위하여 관계법령이 정하는 바에 따라 재단에 소속공무원을 파견할 수 있다.", "cites": 0, "act": 0}, {"no": "제20조", "title": "기록물 관리 등", "html": "제20조(기록물 관리 등) 재단은 <mark class=\"cite-current\" tabindex=\"0\" data-oc=\"제20조\" data-law=\"공공기록물 관리에 관한 법률\" data-clause=\"\">「공공기록물 관리에 관한 법률」</mark>에 따라 재단의 기록물을 관리하여야 한다. \n[본조신설 2021.4.26.]\n\n[종전 제20조는 제21조로 이동&lt;2021.4.26.&gt;]", "cites": 1, "act": 0}, {"no": "제21조", "title": "준용", "html": "제21조(준용) 이 조례에 규정하지 아니한 사항에 대하여는 청소년 관련법령 및 군포시 청소년 관련 자치법규, <mark class=\"cite-local\" tabindex=\"0\" data-oc=\"제21조\" data-law=\"군포시 교육경비 보조에 관한 조례\" data-clause=\"\">「군포시 교육경비 보조에 관한 조례」</mark>, <mark class=\"cite-local\" tabindex=\"0\" data-oc=\"제21조\" data-law=\"군포시 출자·출연 기관의 운영에 관한 기본 조례\" data-clause=\"\">「군포시 출자·출연 기관의 운영에 관한 기본 조례」</mark>, <mark class=\"cite-local\" tabindex=\"0\" data-oc=\"제21조\" data-law=\"군포시 공유재산 관리 조례\" data-clause=\"\">「군포시 공유재산 관리 조례」</mark> 및 <mark class=\"cite-local\" tabindex=\"0\" data-oc=\"제21조\" data-law=\"군포시 회계관리에 관한 규칙\" data-clause=\"\">「군포시 회계관리에 관한 규칙」</mark> 등을 준용한다.&lt;개정 2020.12.31., 2021.4.26.&gt;\n\n[제20조에서 이동&lt;2021.4.26.&gt;]", "cites": 4, "act": 0}], "local_refs": {"군포시교육경비보조에관한조례": {"mst": "2090833", "name": "군포시 교육경비 보조에 관한 조례", "dept": "교육체육과", "enforce_date": "20251210"}, "군포시출자·출연기관의운영에관한기본조례": null, "군포시공유재산관리조례": {"mst": "2055511", "name": "군포시 공유재산 관리 조례", "dept": "회계과", "enforce_date": "20250711"}, "군포시회계관리에관한규칙": {"mst": "1990487", "name": "군포시 회계관리에 관한 규칙", "dept": "회계과", "enforce_date": "20241210"}}, "law_refs": {"민법": {"name": "민법", "law_id": "001706", "clauses": [], "counts": {}, "local_admrul": false}, "지방자치단체출자·출연기관의운영에관한법률": {"name": "지방자치단체 출자·출연 기관의 운영에 관한 법률", "law_id": "012024", "clauses": [], "counts": {}, "local_admrul": false}, "청소년기본법": {"name": "청소년기본법", "law_id": "000816", "clauses": ["제30조"], "counts": {"format": 1}, "local_admrul": false}, "공공기록물관리에관한법률": {"name": "공공기록물 관리에 관한 법률", "law_id": "001963", "clauses": [], "counts": {}, "local_admrul": false}}, "features": {"law": 4, "admrul": 0, "local": 4}, "linked_refs": [], "recommend": {"found": true, "mst": "2106123", "name": "군포시 청소년재단 설립 및 운영 조례", "grades": {"mechanical": 0, "review": 0, "check": 0, "format": 1, "current": 0}, "items_count": 1, "html": "<div class=\"ord\"><h2>군포시 청소년재단 설립 및 운영 조례</h2><div class=\"meta\">시행 2026-01-07 · 정비 항목 1건 · 조례 조문 순서로 정렬</div><div class=\"badges\"><span class=\"badge b-fmt\">📐 서식 정정 1</span></div><div class=\"artsec\" data-oc=\"제12조\"><div class=\"arthd\">조례 제12조</div><details class=\"item citem\" data-sev=\"format\" data-oc=\"제12조\" data-law=\"청소년기본법\" data-clause=\"제30조\"><summary class=\"iline\"><span class=\"tag t-naked\">서식</span><span class=\"law\"><span class=\"ki\" title=\"상위법령\">⚖</span> 「청소년기본법」 제30조</span></summary><div class=\"act\">(서식만 정비) \"<span class=\"fx-old\">청소년기본법 제30조</span>\"를 \"<span class=\"fx-new\"><ins class=\"fx-brk\">「</ins>청소년기본법<ins class=\"fx-brk\">」</ins> 제30조</span>\"로 정정 — <b>내용 변경은 없음</b> (이 조례 제12조)</div><div class=\"basis\">기준일 — 조례 시행 <b>2026-01-07</b> · 당시 법령본 <b>2026-01-02</b> → 현행 조문 <b>2026-10-29</b></div></details></div></div>", "css": "\n/* 변수는 .page(독립 권고서)·.ord(대시보드 주입 블록)에만 — :root 로 두면 대시보드의\n   자체 변수를 덮어써 색이 바뀐다. 두 루트에 한정해 주입 시 오염을 막는다. */\n.page, .ord { --navy:#13325b; --navy2:#1d4e89;\n  --mech:#1d4ed8; --rev:#b45309; --chk:#52525b; --fmt:#6d28d9; --cur:#15803d;\n  --ink:#1f2937; --muted:#6b7280; --line:#d8dee6; --soft:#f6f8fb; }\n* { box-sizing: border-box; }\n/* 독립 권고서 페이지 한정(body.report·.page) — 대시보드 주입 시 충돌 방지.\n   대시보드는 자체 body/h1/.cards/.sub/.card 를 가져 prefix 없으면 덮어쓴다. */\nbody.report { font-family: \"Malgun Gothic\",\"맑은 고딕\",system-ui,sans-serif;\n       color:var(--ink); margin:0; background:#eef1f5; line-height:1.55;\n       -webkit-text-size-adjust:100%; }\n.page { max-width:840px; margin:24px auto; padding:38px 44px 52px; background:#fff;\n        border-top:4px solid var(--navy); box-shadow:0 1px 5px rgba(15,33,66,.10); }\n/* 문서 머리 — 공문 단정형(머리표·제목·요지, 아래 굵은 밑줄) */\n.page .dochd { border-bottom:2px solid var(--navy); padding-bottom:13px; margin-bottom:22px; }\n.page .dochd .kicker { font-size:11.5px; letter-spacing:3px; color:var(--navy2);\n        font-weight:700; margin:0 0 6px; }\n.page h1 { font-size:22px; line-height:1.34; margin:0; color:var(--navy);\n     font-weight:700; letter-spacing:-.3px; }\n.page .sub { color:var(--muted); font-size:12.5px; margin-top:7px; }\n.page .cards { display:flex; gap:10px; flex-wrap:wrap; margin:0 0 20px; }\n.page .card { flex:1 1 138px; border:1px solid var(--line); border-top:3px solid var(--chk);\n        border-radius:6px; padding:12px 15px; }\n.page .card .n { font-size:25px; font-weight:700; line-height:1; color:var(--ink); }\n.page .card .t { font-size:12.5px; color:var(--muted); margin-top:6px; }\n.page .g-mech { border-top-color:var(--mech);} .page .g-mech .n { color:var(--mech);}\n.page .g-rev { border-top-color:var(--rev);} .page .g-rev .n { color:var(--rev);}\n.page .g-chk { border-top-color:var(--chk);} .page .g-chk .n { color:var(--chk);}\n.page .g-fmt { border-top-color:var(--fmt);} .page .g-fmt .n { color:var(--fmt);}\n.page .g-cur { border-top-color:var(--cur);} .page .g-cur .n { color:var(--cur);}\n.ord { border:1px solid var(--line); border-radius:7px; padding:18px 20px;\n       margin:0 0 16px; page-break-inside:avoid; }\n.ord h2 { font-size:16.5px; margin:0 0 3px; color:var(--navy); font-weight:700;\n          padding-left:10px; border-left:4px solid var(--navy); }\n.ord .meta { color:var(--muted); font-size:12px; margin:0 0 12px; padding-left:14px; }\n.badges { margin:0 0 12px; }\n.badge { display:inline-block; font-size:11.5px; padding:2px 10px; border-radius:4px;\n         margin-right:6px; border:1px solid currentColor; background:#fff; font-weight:600; }\n.b-mech { color:var(--mech);} .b-rev { color:var(--rev);}\n.b-chk { color:var(--chk);} .b-fmt { color:var(--fmt);}\n.artsec { margin:0 0 8px; }\n.arthd { font-size:13px; font-weight:700; color:var(--navy); background:var(--soft);\n         border-left:3px solid var(--navy2); padding:5px 11px; border-radius:0 4px 4px 0;\n         margin:14px 0 6px; }\n.item { border-top:1px solid #f3f4f6; padding:9px 0 9px 10px; }\n.iline { margin-bottom:3px; }\n.item .tag { font-size:11px; font-weight:700; padding:1px 7px; border-radius:6px;\n             margin-right:8px; white-space:nowrap; }\n.t-mech { background:#dbeafe; color:#1e40af;} .t-rev { background:#fef3c7; color:#92400e;}\n.t-chk { background:#f3f4f6; color:#374151;}\n.t-naked { background:#ede9fe; color:#5b21b6;}\n.t-cur { background:#dcfce7; color:#166534;}\n.t-space { background:#fef9c3; color:#854d0e;}\ndetails.citem.cur > summary { opacity:.72; }\ndetails.citem.cur .law { font-weight:500; }\n/* 접이식 인용 항목(대시보드 우측) — 기본 접힘, 좌측 인용 클릭 시 펼침 */\ndetails.citem { border-top:1px solid #f3f4f6; padding:0; border-left:4px solid transparent; }\n/* 심각도 좌측 색바(4px) — .focus 는 box-shadow 라 색바와 공존 */\ndetails.citem[data-sev=\"mechanical\"] { border-left-color:var(--mech); }\ndetails.citem[data-sev=\"review\"] { border-left-color:var(--rev); }\ndetails.citem[data-sev=\"check\"] { border-left-color:var(--chk); }\ndetails.citem[data-sev=\"format\"] { border-left-color:var(--fmt); }\ndetails.citem[data-sev=\"current\"] { border-left-color:#d1d5db; }\n/* 변경없음 숨기기(우측 헤더 체크) — .drec 는 serve.py 컨테이너 */\n.drec.hide-cur details.citem.cur { display:none; }\ndetails.citem > summary { list-style:none; cursor:pointer; padding:9px 10px 9px 8px;\n    display:flex; align-items:center; gap:5px; flex-wrap:wrap; }\ndetails.citem > summary::-webkit-details-marker { display:none; }\ndetails.citem > summary::before { content:\"▸\"; color:#9ca3af; font-size:11px; margin-right:2px; }\ndetails.citem[open] > summary::before { content:\"▾\"; color:var(--navy2); }\ndetails.citem[open] { background:#fbfcfe; }\ndetails.citem > .act { padding:2px 10px 0; } details.citem > .basis { padding:0 10px; }\ndetails.citem > .diff { margin:6px 10px 10px; }\ndetails.citem.focus { box-shadow:inset 3px 0 0 var(--navy2); }\n.item .law { font-size:13px; font-weight:600; color:#374151; }\n.item .law .ki { font-weight:400; font-size:12px; margin-right:1px; }\n.item a.ais { font-size:11px; font-weight:600; color:#0369a1; background:#e0f2fe;\n    border-radius:6px; padding:1px 7px; margin-left:6px; text-decoration:none; white-space:nowrap; }\n.item a.ais:hover { background:#bae6fd; }\n.item .act { font-size:13.5px; margin:3px 0; color:var(--ink); }\n/* 검토 문안 내 정정 강조 — 현재 표기(회색) → 정정 표기(초록), 삽입 「」는 진한 초록 */\n.act .fx-old { background:#f1f5f9; color:#64748b; border-radius:3px; padding:0 3px; }\n.act .fx-new { background:#eafaf0; color:#15803d; border-radius:3px; padding:0 3px; font-weight:600; }\n.act .fx-new .fx-brk { background:#bbf7d0; color:#166534; font-weight:800; border-radius:2px;\n    padding:0 1px; margin:0 1px; text-decoration:none; }\n.basis { font-size:11.5px; color:var(--muted); margin:4px 0 6px; }\n.basis b { color:#374151; font-weight:600; }\n.ordtext { font-size:12.5px; color:var(--ink); background:var(--soft); border:1px solid var(--line);\n           border-left:3px solid var(--navy2); border-radius:0 6px 6px 0; padding:8px 11px;\n           margin:5px 0 9px; white-space:pre-wrap; line-height:1.7; }\n.ordtext b { color:var(--navy); margin-right:5px; }\nmark.cite-law { background:#eff6ff; color:#1e3a8a;\n   text-decoration:underline; text-decoration-color:#2563eb; text-underline-offset:2px;\n   border-radius:2px; padding:0 1px; }\nmark.cite-naked { background:#f5f3ff; color:#5b21b6;\n   text-decoration:underline dashed; text-decoration-color:#7c3aed; text-underline-offset:2px;\n   border-radius:2px; padding:0 1px; }\nmark.cite-local { background:#f1f5f9; color:#475569;\n   text-decoration:underline dotted; text-decoration-color:#94a3b8; text-underline-offset:2px;\n   border-radius:2px; padding:0 1px; }\n.page .leg { font-size:12px; color:var(--muted); margin:0 0 18px; display:flex; gap:14px;\n        flex-wrap:wrap; align-items:center; }\n.page .leg mark { padding:0 4px; border-radius:2px; }\n.item .ev { font-size:12px; color:#6b7280; white-space:pre-wrap;\n            background:#f9fafb; border-radius:6px; padding:7px 9px; margin-top:6px; }\n.diff { border:1px solid #eef0f3; border-radius:6px; overflow:hidden; margin-top:6px; }\n.diff .diff-uni { font-size:12px; padding:7px 9px; white-space:pre-wrap;\n  word-break:keep-all; overflow-wrap:anywhere; color:#374151; line-height:1.55; }\n.diff .diff-split { display:none; }                 /* 대시보드 기본 = 통합(합쳐) 보기 */\n/* 나란히 모드(대시보드 토글) · 인쇄 권고서(.page)는 당시·현행 나란히 */\n.diff-mode-split .diff .diff-uni, .page .diff .diff-uni { display:none; }\n.diff-mode-split .diff .diff-split, .page .diff .diff-split { display:block; }\n.drow { display:flex; gap:8px; font-size:12px; padding:6px 9px; }\n.drow + .drow { border-top:1px solid #f1f3f5; }\n.dlabel { flex:0 0 34px; font-weight:700; font-size:11px; padding-top:1px; }\n.dlabel.was { color:#b91c1c; } .dlabel.now { color:#15803d; }\n.dtext { flex:1; white-space:pre-wrap; word-break:keep-all; overflow-wrap:anywhere; color:#374151; line-height:1.5; }\nmark.d { background:#fee2e2; color:#991b1b; text-decoration:line-through;\n         border-radius:2px; padding:0 1px; }\nmark.i { background:#dcfce7; color:#166534; border-radius:2px; padding:0 1px; }\nmark.pt { background:#fee2e2; color:#dc2626; font-weight:700; border-radius:2px;\n          padding:0 2px; cursor:help; }\n.page footer { color:#9aa3af; font-size:11.5px; margin-top:34px; padding-top:14px;\n         border-top:1px solid var(--line); text-align:center; }\n@media print {\n  @page { size:A4; margin:16mm; }\n  body { background:#fff; }\n  .page { max-width:none; margin:0; padding:0; border-top:none; box-shadow:none; }\n  .ord, .card { border-color:#c4cbd4; }\n  .dochd { border-bottom-color:#000; }\n  mark.d, mark.i, mark.pt, .ordtext mark, .card, .badge {\n    -webkit-print-color-adjust:exact; print-color-adjust:exact; }\n}\n"}}